RH_Package/RH_Metrics.py
RH_Package/__init__.py
RH_Package-0.1.1.dist-info/LICENSE
RH_Package-0.1.1.dist-info/METADATA
RH_Package-0.1.1.dist-info/WHEEL
RH_Package-0.1.1.dist-info/top_level.txt
RH_Package-0.1.1.dist-info/RECORD
