Metadata-Version: 2.1
Name: RH_Package
Version: 0.1.1
Summary: Package for RHI Metrics evaluation
Author: Praveen Katwe, Naman Kabadi
Author-email: c121007@iiit-bh.ac.in, namankabadi50@gmail.com
License: MIT
Classifier: Programming Language :: Python :: 3
Classifier: License :: OSI Approved :: MIT License
Classifier: Operating System :: OS Independent
Requires-Python: >=3.10
License-File: LICENSE
Requires-Dist: spacy
Requires-Dist: rouge-score
Requires-Dist: numpy
Requires-Dist: matplotlib
Requires-Dist: seaborn
Requires-Dist: pandas
Requires-Dist: nltk
Requires-Dist: bert-score
Requires-Dist: transformers
